masterblog_core/__init__.py
masterblog_core/models/__init__.py
masterblog_core/models/blog.py
masterblog_core/models/post.py
masterblog_core/storage/__init__.py
masterblog_core/storage/filestore.py
masterblog_core/storage/sequence.py
masterblog_core-0.1.1.post1.dist-info/licenses/LICENSE
masterblog_core-0.1.1.post1.dist-info/METADATA
masterblog_core-0.1.1.post1.dist-info/WHEEL
masterblog_core-0.1.1.post1.dist-info/top_level.txt
masterblog_core-0.1.1.post1.dist-info/RECORD
