Metadata-Version: 2.4
Name: masterblog-core
Version: 0.1.1.post1
Summary: A blog engine core with JSON storage
Author: Paul Wosch
Maintainer: Paul Wosch
License-Expression: MIT
Requires-Python: >=3.10
License-File: LICENSE
Dynamic: license-file
